CHANGES.txt
README.txt
buildout.cfg
setup.py
src/d2m/__init__.py
src/d2m.rendersource.egg-info/PKG-INFO
src/d2m.rendersource.egg-info/SOURCES.txt
src/d2m.rendersource.egg-info/dependency_links.txt
src/d2m.rendersource.egg-info/entry_points.txt
src/d2m.rendersource.egg-info/namespace_packages.txt
src/d2m.rendersource.egg-info/not-zip-safe
src/d2m.rendersource.egg-info/requires.txt
src/d2m.rendersource.egg-info/top_level.txt
src/d2m/rendersource/__init__.py
src/d2m/rendersource/configure.zcml
src/d2m/rendersource/ftesting.zcml
src/d2m/rendersource/rest.py
src/d2m/rendersource/ftests/__init__.py
src/d2m/rendersource/ftests/tests_functional.py
src/d2m/rendersource/ftests/directives/__init__.py
src/d2m/rendersource/ftests/directives/app.py
src/d2m/rendersource/ftests/directives/app_templates/base.rst
src/d2m/rendersource/ftests/directives/app_templates/include.txt
src/d2m/rendersource/ftests/directives/app_templates/index.pt
src/d2m/rendersource/ftests/directives/static/README.txt
src/d2m/rendersource/ftests/directives/static/grok.css
