Metadata-Version: 1.0
Name: d2m.rendersource
Version: 0.4
Summary: Grok source renderers
Home-page: UNKNOWN
Author: d2m
Author-email: michael@d2m.at
License: ZPL
Platform: UNKNOWN
